[
  {
    "word": "glaze",
    "syllables": [
      "glaze"
    ],
    "pronunciation": "ɡlāz",
    "parts": [
      {
        "part": "verb",
        "variants": [
          {
            "part": "past tense",
            "variant": "glazed"
          },
          {
            "part": "past participle",
            "variant": "glazed"
          }
        ],
        "definitions": [
          {
            "definition": "fit panes of glass into (a window or doorframe or similar structure).",
            "examples": [
              "windows can be glazed using laminated glass"
            ]
          },
          {
            "definition": "enclose or cover with glass.",
            "examples": [
              "the verandas were glazed in"
            ]
          },
          {
            "definition": "overlay or cover (food, fabric, etc.) with a smooth, shiny coating or finish.",
            "examples": [
              "new potatoes that had been glazed in mint-flavored butter"
            ],
            "synonyms": [
              "varnish",
              "enamel",
              "lacquer",
              "japan",
              "shellac",
              "paint; Moregloss \"the pots are glazed when dry\"cover",
              "coat; ice",
              "frost \"pastry glazed with caramel\""
            ]
          },
          {
            "definition": "lose brightness and animation.",
            "examples": [
              "the prospect makes my eyes glaze over with boredom"
            ],
            "synonyms": [
              "become glassy",
              "go blank; Moremist over",
              "film over \"his eyes glazed over\""
            ]
          }
        ]
      }
    ]
  }
]