{
  "word": "roadstead",
  "syllables": [
    "road",
    "stead"
  ],
  "pronunciation": "ˈrōdsted",
  "parts": [
    {
      "part": "noun",
      "variants": [
        {
          "part": "noun",
          "variant": "roadstead"
        },
        {
          "part": "plural noun",
          "variant": "roadsteads"
        }
      ],
      "definitions": [
        {
          "definition": "a sheltered stretch of water near the shore in which ships can ride at anchor."
        }
      ]
    }
  ]
}